{
  "-1": "неизвестный",
  "100": "эмиссия",
  "200": "перевод",
  "201": "передача",
  "202": "перевод DREAM",
  "203": "перевод субагенту",
  "204": "перевод donate",
  "205": "перевод агенту",
  "206": "безадресный перевод",
  "210": "транзитный перевод",
  "230": "перевод WSDL",
  "233": "продажа WSDL",
  "234": "перевод DONATE_WSDL",
  "235": "перевод агенту WSDL",
  "300": "оплата",
  "302": "оплата DREAM",
  "303": "запрос оплаты",
  "304": "инвойс",
  "305": "предоплата",
  "306": "задержанная оплата",
  "310": "транзитная оплата",
  "330": "оплата WSDL",
  "334": "инвойс WSDL",
  "344": "инвойс SMS",
  "400": "вывод",
  "500": "обмен",
  "600": "DISCHARGEMENT",
  "700": "возврат",
  "750": "возврат мерчанта",
  "751": "возврат части операции",
  "800": "подтверждение",
  "900": "ALL"
}